k8s_jobs/__init__.py
k8s_jobs/config.py
k8s_jobs/exceptions.py
k8s_jobs/file_reloader.py
k8s_jobs/manager.py
k8s_jobs/spec.py
k8s_jobs-0.2.0.dist-info/WHEEL
k8s_jobs-0.2.0.dist-info/METADATA
k8s_jobs-0.2.0.dist-info/RECORD
