Metadata-Version: 2.1
Name: k8s-jobs
Version: 0.2.0
Summary: Async Job Manager + AWS Batch Replacement for K8s
Home-page: https://github.com/danieltahara/k8s-jobs
License: Apache-2.0
Author: Daniel Tahara
Author-email: dktahara@gmail.com
Requires-Python: >=3.6,<4
Classifier: License :: OSI Approved :: Apache Software License
Classifier: Programming Language :: Python :: 3
Classifier: Programming Language :: Python :: 3.6
Classifier: Programming Language :: Python :: 3.7
Classifier: Programming Language :: Python :: 3.8
Requires-Dist: dataclasses (>=0.6.0,<0.7.0)
Requires-Dist: jinja2 (>=2.10,<3.0)
Requires-Dist: kubernetes (>=10.0,<11.0)
Project-URL: Repository, https://github.com/danieltahara/k8s-jobs
